LICENSE
MANIFEST.in
README.md
setup.py
r3frame/__init__.py
r3frame/atom.py
r3frame/globs.py
r3frame/quotes.py
r3frame/util.py
r3frame/version.py
r3frame.egg-info/PKG-INFO
r3frame.egg-info/SOURCES.txt
r3frame.egg-info/dependency_links.txt
r3frame.egg-info/requires.txt
r3frame.egg-info/top_level.txt
r3frame/app/__init__.py
r3frame/app/base.py
r3frame/app/camera.py
r3frame/app/clock.py
r3frame/app/event.py
r3frame/app/input.py
r3frame/app/proc.py
r3frame/app/renderer.py
r3frame/app/scene.py
r3frame/app/window.py
r3frame/app/resource/__init__.py
r3frame/app/resource/animation.py
r3frame/app/resource/base.py
r3frame/app/resource/image.py
r3frame/app/resource/manager.py
r3frame/app/ui/__init__.py
r3frame/app/ui/base.py
r3frame/app/ui/element.py
r3frame/assets/fonts/megamax.ttf
r3frame/assets/images/r3-logo.ico
r3frame/game/__init__.py
r3frame/game/obj.py
r3frame/game/partition.py
r3frame/game/vfx.py
r3frame/game/world.py